coef_analysis/__init__.py
coef_analysis/correlation.py
coef_analysis-0.3.dist-info/LICENSE
coef_analysis-0.3.dist-info/METADATA
coef_analysis-0.3.dist-info/WHEEL
coef_analysis-0.3.dist-info/top_level.txt
coef_analysis-0.3.dist-info/RECORD
