Metadata-Version: 2.1
Name: coef-analysis
Version: 0.3
Summary: Biblioteca para análise de coeficientes de correlação
Home-page: https://github.com/leo-areias/Analise-de-Coeficiente.git
Author: Leonardo Areias
Author-email: leorareias@gmail.com
License: MIT
Platform: UNKNOWN
Classifier: Programming Language :: Python :: 3
Classifier: License :: OSI Approved :: MIT License
Classifier: Operating System :: OS Independent
Requires-Python: >=3.6
License-File: LICENSE
Requires-Dist: pandas
Requires-Dist: numpy
